[
  {
    "id": 110011,
    "characterMasterId": 110010,
    "episodeMasterId": 110011,
    "episodeOrder": "First",
    "requiredCharacterLevel": 1
  },
  {
    "id": 110012,
    "characterMasterId": 110010,
    "episodeMasterId": 110012,
    "episodeOrder": "Second",
    "requiredCharacterLevel": 25
  },
  {
    "id": 110021,
    "characterMasterId": 110020,
    "episodeMasterId": 110021,
    "episodeOrder": "First",
    "requiredCharacterLevel": 1
  },
  {
    "id": 110022,
    "characterMasterId": 110020,
    "episodeMasterId": 110022,
    "episodeOrder": "Second",
    "requiredCharacterLevel": 25
  },
  {
    "id": 110031,
    "characterMasterId": 110030,
    "episodeMasterId": 110031,
    "episodeOrder": "First",
    "requiredCharacterLevel": 1
  },
  {
    "id": 110032,
    "characterMasterId": 110030,
    "episodeMasterId": 110032,
    "episodeOrder": "Second",
    "requiredCharacterLevel": 25
  },
  {
    "id": 110041,
    "characterMasterId": 110040,
    "episodeMasterId": 110041,
    "episodeOrder": "First",
    "requiredCharacterLevel": 1
  },
  {
    "id": 110042,
    "characterMasterId": 110040,
    "episodeMasterId": 110042,
    "episodeOrder": "Second",
    "requiredCharacterLevel": 25
  },
  {
    "id": 110051,
    "characterMasterId": 110050,
    "episodeMasterId": 110051,
    "episodeOrder": "First",
    "requiredCharacterLevel": 1
  },
  {
    "id": 110052,
    "characterMasterId": 110050,
    "episodeMasterId": 110052,
    "episodeOrder": "Second",
    "requiredCharacterLevel": 25
  },
  {
    "id": 110061,
    "characterMasterId": 110060,
    "episodeMasterId": 110061,
    "episodeOrder": "First",
    "requiredCharacterLevel": 1
  },
  {
    "id": 110062,
    "characterMasterId": 110060,
    "episodeMasterId": 110062,
    "episodeOrder": "Second",
    "requiredCharacterLevel": 25
  },
  {
    "id": 110071,
    "characterMasterId": 110070,
    "episodeMasterId": 110071,
    "episodeOrder": "First",
    "requiredCharacterLevel": 1
  },
  {
    "id": 110072,
    "characterMasterId": 110070,
    "episodeMasterId": 110072,
    "episodeOrder": "Second",
    "requiredCharacterLevel": 25
  },
  {
    "id": 110081,
    "characterMasterId": 110080,
    "episodeMasterId": 110081,
    "episodeOrder": "First",
    "requiredCharacterLevel": 1
  },
  {
    "id": 110082,
    "characterMasterId": 110080,
    "episodeMasterId": 110082,
    "episodeOrder": "Second",
    "requiredCharacterLevel": 25
  },
  {
    "id": 110091,
    "characterMasterId": 110090,
    "episodeMasterId": 110091,
    "episodeOrder": "First",
    "requiredCharacterLevel": 1
  },
  {
    "id": 110092,
    "characterMasterId": 110090,
    "episodeMasterId": 110092,
    "episodeOrder": "Second",
    "requiredCharacterLevel": 25
  },
  {
    "id": 110101,
    "characterMasterId": 110100,
    "episodeMasterId": 110101,
    "episodeOrder": "First",
    "requiredCharacterLevel": 1
  },
  {
    "id": 110102,
    "characterMasterId": 110100,
    "episodeMasterId": 110102,
    "episodeOrder": "Second",
    "requiredCharacterLevel": 25
  },
  {
    "id": 110111,
    "characterMasterId": 110110,
    "episodeMasterId": 110111,
    "episodeOrder": "First",
    "requiredCharacterLevel": 1
  },
  {
    "id": 110112,
    "characterMasterId": 110110,
    "episodeMasterId": 110112,
    "episodeOrder": "Second",
    "requiredCharacterLevel": 25
  },
  {
    "id": 110121,
    "characterMasterId": 110120,
    "episodeMasterId": 110121,
    "episodeOrder": "First",
    "requiredCharacterLevel": 1
  },
  {
    "id": 110122,
    "characterMasterId": 110120,
    "episodeMasterId": 110122,
    "episodeOrder": "Second",
    "requiredCharacterLevel": 25
  },
  {
    "id": 110131,
    "characterMasterId": 110130,
    "episodeMasterId": 110131,
    "episodeOrder": "First",
    "requiredCharacterLevel": 1
  },
  {
    "id": 110132,
    "characterMasterId": 110130,
    "episodeMasterId": 110132,
    "episodeOrder": "Second",
    "requiredCharacterLevel": 25
  },
  {
    "id": 110141,
    "characterMasterId": 110140,
    "episodeMasterId": 110141,
    "episodeOrder": "First",
    "requiredCharacterLevel": 1
  },
  {
    "id": 110142,
    "characterMasterId": 110140,
    "episodeMasterId": 110142,
    "episodeOrder": "Second",
    "requiredCharacterLevel": 25
  },
  {
    "id": 110151,
    "characterMasterId": 110150,
    "episodeMasterId": 110151,
    "episodeOrder": "First",
    "requiredCharacterLevel": 1
  },
  {
    "id": 110152,
    "characterMasterId": 110150,
    "episodeMasterId": 110152,
    "episodeOrder": "Second",
    "requiredCharacterLevel": 25
  },
  {
    "id": 110161,
    "characterMasterId": 110160,
    "episodeMasterId": 110161,
    "episodeOrder": "First",
    "requiredCharacterLevel": 1
  },
  {
    "id": 110162,
    "characterMasterId": 110160,
    "episodeMasterId": 110162,
    "episodeOrder": "Second",
    "requiredCharacterLevel": 25
  },
  {
    "id": 110171,
    "characterMasterId": 110170,
    "episodeMasterId": 110171,
    "episodeOrder": "First",
    "requiredCharacterLevel": 1
  },
  {
    "id": 110172,
    "characterMasterId": 110170,
    "episodeMasterId": 110172,
    "episodeOrder": "Second",
    "requiredCharacterLevel": 25
  },
  {
    "id": 110181,
    "characterMasterId": 110180,
    "episodeMasterId": 110181,
    "episodeOrder": "First",
    "requiredCharacterLevel": 1
  },
  {
    "id": 110182,
    "characterMasterId": 110180,
    "episodeMasterId": 110182,
    "episodeOrder": "Second",
    "requiredCharacterLevel": 25
  },
  {
    "id": 110191,
    "characterMasterId": 110190,
    "episodeMasterId": 110191,
    "episodeOrder": "First",
    "requiredCharacterLevel": 1
  },
  {
    "id": 110192,
    "characterMasterId": 110190,
    "episodeMasterId": 110192,
    "episodeOrder": "Second",
    "requiredCharacterLevel": 25
  },
  {
    "id": 110201,
    "characterMasterId": 110200,
    "episodeMasterId": 110201,
    "episodeOrder": "First",
    "requiredCharacterLevel": 1
  },
  {
    "id": 110202,
    "characterMasterId": 110200,
    "episodeMasterId": 110202,
    "episodeOrder": "Second",
    "requiredCharacterLevel": 25
  },
  {
    "id": 110211,
    "characterMasterId": 110210,
    "episodeMasterId": 110211,
    "episodeOrder": "First",
    "requiredCharacterLevel": 1
  },
  {
    "id": 110212,
    "characterMasterId": 110210,
    "episodeMasterId": 110212,
    "episodeOrder": "Second",
    "requiredCharacterLevel": 25
  },
  {
    "id": 120011,
    "characterMasterId": 120010,
    "episodeMasterId": 120011,
    "episodeOrder": "First",
    "requiredCharacterLevel": 1
  },
  {
    "id": 120012,
    "characterMasterId": 120010,
    "episodeMasterId": 120012,
    "episodeOrder": "Second",
    "requiredCharacterLevel": 25
  },
  {
    "id": 120021,
    "characterMasterId": 120020,
    "episodeMasterId": 120021,
    "episodeOrder": "First",
    "requiredCharacterLevel": 1
  },
  {
    "id": 120022,
    "characterMasterId": 120020,
    "episodeMasterId": 120022,
    "episodeOrder": "Second",
    "requiredCharacterLevel": 25
  },
  {
    "id": 120031,
    "characterMasterId": 120030,
    "episodeMasterId": 120031,
    "episodeOrder": "First",
    "requiredCharacterLevel": 1
  },
  {
    "id": 120032,
    "characterMasterId": 120030,
    "episodeMasterId": 120032,
    "episodeOrder": "Second",
    "requiredCharacterLevel": 25
  },
  {
    "id": 120041,
    "characterMasterId": 120040,
    "episodeMasterId": 120041,
    "episodeOrder": "First",
    "requiredCharacterLevel": 1
  },
  {
    "id": 120042,
    "characterMasterId": 120040,
    "episodeMasterId": 120042,
    "episodeOrder": "Second",
    "requiredCharacterLevel": 25
  },
  {
    "id": 120051,
    "characterMasterId": 120050,
    "episodeMasterId": 120051,
    "episodeOrder": "First",
    "requiredCharacterLevel": 1
  },
  {
    "id": 120052,
    "characterMasterId": 120050,
    "episodeMasterId": 120052,
    "episodeOrder": "Second",
    "requiredCharacterLevel": 25
  },
  {
    "id": 120061,
    "characterMasterId": 120060,
    "episodeMasterId": 120061,
    "episodeOrder": "First",
    "requiredCharacterLevel": 1
  },
  {
    "id": 120062,
    "characterMasterId": 120060,
    "episodeMasterId": 120062,
    "episodeOrder": "Second",
    "requiredCharacterLevel": 25
  },
  {
    "id": 120071,
    "characterMasterId": 120070,
    "episodeMasterId": 120071,
    "episodeOrder": "First",
    "requiredCharacterLevel": 1
  },
  {
    "id": 120072,
    "characterMasterId": 120070,
    "episodeMasterId": 120072,
    "episodeOrder": "Second",
    "requiredCharacterLevel": 25
  },
  {
    "id": 120081,
    "characterMasterId": 120080,
    "episodeMasterId": 120081,
    "episodeOrder": "First",
    "requiredCharacterLevel": 1
  },
  {
    "id": 120082,
    "characterMasterId": 120080,
    "episodeMasterId": 120082,
    "episodeOrder": "Second",
    "requiredCharacterLevel": 25
  },
  {
    "id": 120091,
    "characterMasterId": 120090,
    "episodeMasterId": 120091,
    "episodeOrder": "First",
    "requiredCharacterLevel": 1
  },
  {
    "id": 120092,
    "characterMasterId": 120090,
    "episodeMasterId": 120092,
    "episodeOrder": "Second",
    "requiredCharacterLevel": 25
  },
  {
    "id": 120101,
    "characterMasterId": 120100,
    "episodeMasterId": 120101,
    "episodeOrder": "First",
    "requiredCharacterLevel": 1
  },
  {
    "id": 120102,
    "characterMasterId": 120100,
    "episodeMasterId": 120102,
    "episodeOrder": "Second",
    "requiredCharacterLevel": 25
  },
  {
    "id": 120111,
    "characterMasterId": 120110,
    "episodeMasterId": 120111,
    "episodeOrder": "First",
    "requiredCharacterLevel": 1
  },
  {
    "id": 120112,
    "characterMasterId": 120110,
    "episodeMasterId": 120112,
    "episodeOrder": "Second",
    "requiredCharacterLevel": 25
  },
  {
    "id": 120121,
    "characterMasterId": 120120,
    "episodeMasterId": 120121,
    "episodeOrder": "First",
    "requiredCharacterLevel": 1
  },
  {
    "id": 120122,
    "characterMasterId": 120120,
    "episodeMasterId": 120122,
    "episodeOrder": "Second",
    "requiredCharacterLevel": 25
  },
  {
    "id": 120131,
    "characterMasterId": 120130,
    "episodeMasterId": 120131,
    "episodeOrder": "First",
    "requiredCharacterLevel": 1
  },
  {
    "id": 120132,
    "characterMasterId": 120130,
    "episodeMasterId": 120132,
    "episodeOrder": "Second",
    "requiredCharacterLevel": 25
  },
  {
    "id": 120141,
    "characterMasterId": 120140,
    "episodeMasterId": 120141,
    "episodeOrder": "First",
    "requiredCharacterLevel": 1
  },
  {
    "id": 120142,
    "characterMasterId": 120140,
    "episodeMasterId": 120142,
    "episodeOrder": "Second",
    "requiredCharacterLevel": 25
  },
  {
    "id": 120151,
    "characterMasterId": 120150,
    "episodeMasterId": 120151,
    "episodeOrder": "First",
    "requiredCharacterLevel": 1
  },
  {
    "id": 120152,
    "characterMasterId": 120150,
    "episodeMasterId": 120152,
    "episodeOrder": "Second",
    "requiredCharacterLevel": 25
  },
  {
    "id": 120161,
    "characterMasterId": 120160,
    "episodeMasterId": 120161,
    "episodeOrder": "First",
    "requiredCharacterLevel": 1
  },
  {
    "id": 120162,
    "characterMasterId": 120160,
    "episodeMasterId": 120162,
    "episodeOrder": "Second",
    "requiredCharacterLevel": 25
  },
  {
    "id": 120171,
    "characterMasterId": 120170,
    "episodeMasterId": 120171,
    "episodeOrder": "First",
    "requiredCharacterLevel": 1
  },
  {
    "id": 120172,
    "characterMasterId": 120170,
    "episodeMasterId": 120172,
    "episodeOrder": "Second",
    "requiredCharacterLevel": 25
  },
  {
    "id": 120181,
    "characterMasterId": 120180,
    "episodeMasterId": 120181,
    "episodeOrder": "First",
    "requiredCharacterLevel": 1
  },
  {
    "id": 120182,
    "characterMasterId": 120180,
    "episodeMasterId": 120182,
    "episodeOrder": "Second",
    "requiredCharacterLevel": 25
  },
  {
    "id": 120191,
    "characterMasterId": 120190,
    "episodeMasterId": 120191,
    "episodeOrder": "First",
    "requiredCharacterLevel": 1
  },
  {
    "id": 120192,
    "characterMasterId": 120190,
    "episodeMasterId": 120192,
    "episodeOrder": "Second",
    "requiredCharacterLevel": 25
  },
  {
    "id": 120201,
    "characterMasterId": 120200,
    "episodeMasterId": 120201,
    "episodeOrder": "First",
    "requiredCharacterLevel": 1
  },
  {
    "id": 120202,
    "characterMasterId": 120200,
    "episodeMasterId": 120202,
    "episodeOrder": "Second",
    "requiredCharacterLevel": 25
  },
  {
    "id": 120211,
    "characterMasterId": 120210,
    "episodeMasterId": 120211,
    "episodeOrder": "First",
    "requiredCharacterLevel": 1
  },
  {
    "id": 120212,
    "characterMasterId": 120210,
    "episodeMasterId": 120212,
    "episodeOrder": "Second",
    "requiredCharacterLevel": 25
  },
  {
    "id": 130011,
    "characterMasterId": 130010,
    "episodeMasterId": 130011,
    "episodeOrder": "First",
    "requiredCharacterLevel": 1
  },
  {
    "id": 130012,
    "characterMasterId": 130010,
    "episodeMasterId": 130012,
    "episodeOrder": "Second",
    "requiredCharacterLevel": 25
  },
  {
    "id": 130021,
    "characterMasterId": 130020,
    "episodeMasterId": 130021,
    "episodeOrder": "First",
    "requiredCharacterLevel": 1
  },
  {
    "id": 130022,
    "characterMasterId": 130020,
    "episodeMasterId": 130022,
    "episodeOrder": "Second",
    "requiredCharacterLevel": 25
  },
  {
    "id": 130031,
    "characterMasterId": 130030,
    "episodeMasterId": 130031,
    "episodeOrder": "First",
    "requiredCharacterLevel": 1
  },
  {
    "id": 130032,
    "characterMasterId": 130030,
    "episodeMasterId": 130032,
    "episodeOrder": "Second",
    "requiredCharacterLevel": 25
  },
  {
    "id": 130041,
    "characterMasterId": 130040,
    "episodeMasterId": 130041,
    "episodeOrder": "First",
    "requiredCharacterLevel": 1
  },
  {
    "id": 130042,
    "characterMasterId": 130040,
    "episodeMasterId": 130042,
    "episodeOrder": "Second",
    "requiredCharacterLevel": 25
  },
  {
    "id": 130051,
    "characterMasterId": 130050,
    "episodeMasterId": 130051,
    "episodeOrder": "First",
    "requiredCharacterLevel": 1
  },
  {
    "id": 130052,
    "characterMasterId": 130050,
    "episodeMasterId": 130052,
    "episodeOrder": "Second",
    "requiredCharacterLevel": 25
  },
  {
    "id": 130061,
    "characterMasterId": 130060,
    "episodeMasterId": 130061,
    "episodeOrder": "First",
    "requiredCharacterLevel": 1
  },
  {
    "id": 130062,
    "characterMasterId": 130060,
    "episodeMasterId": 130062,
    "episodeOrder": "Second",
    "requiredCharacterLevel": 25
  },
  {
    "id": 130071,
    "characterMasterId": 130070,
    "episodeMasterId": 130071,
    "episodeOrder": "First",
    "requiredCharacterLevel": 1
  },
  {
    "id": 130072,
    "characterMasterId": 130070,
    "episodeMasterId": 130072,
    "episodeOrder": "Second",
    "requiredCharacterLevel": 25
  },
  {
    "id": 130081,
    "characterMasterId": 130080,
    "episodeMasterId": 130081,
    "episodeOrder": "First",
    "requiredCharacterLevel": 1
  },
  {
    "id": 130082,
    "characterMasterId": 130080,
    "episodeMasterId": 130082,
    "episodeOrder": "Second",
    "requiredCharacterLevel": 25
  },
  {
    "id": 130091,
    "characterMasterId": 130090,
    "episodeMasterId": 130091,
    "episodeOrder": "First",
    "requiredCharacterLevel": 1
  },
  {
    "id": 130092,
    "characterMasterId": 130090,
    "episodeMasterId": 130092,
    "episodeOrder": "Second",
    "requiredCharacterLevel": 25
  },
  {
    "id": 130101,
    "characterMasterId": 130100,
    "episodeMasterId": 130101,
    "episodeOrder": "First",
    "requiredCharacterLevel": 1
  },
  {
    "id": 130102,
    "characterMasterId": 130100,
    "episodeMasterId": 130102,
    "episodeOrder": "Second",
    "requiredCharacterLevel": 25
  },
  {
    "id": 130111,
    "characterMasterId": 130110,
    "episodeMasterId": 130111,
    "episodeOrder": "First",
    "requiredCharacterLevel": 1
  },
  {
    "id": 130112,
    "characterMasterId": 130110,
    "episodeMasterId": 130112,
    "episodeOrder": "Second",
    "requiredCharacterLevel": 25
  },
  {
    "id": 130121,
    "characterMasterId": 130120,
    "episodeMasterId": 130121,
    "episodeOrder": "First",
    "requiredCharacterLevel": 1
  },
  {
    "id": 130122,
    "characterMasterId": 130120,
    "episodeMasterId": 130122,
    "episodeOrder": "Second",
    "requiredCharacterLevel": 25
  },
  {
    "id": 130131,
    "characterMasterId": 130130,
    "episodeMasterId": 130131,
    "episodeOrder": "First",
    "requiredCharacterLevel": 1
  },
  {
    "id": 130132,
    "characterMasterId": 130130,
    "episodeMasterId": 130132,
    "episodeOrder": "Second",
    "requiredCharacterLevel": 25
  },
  {
    "id": 130141,
    "characterMasterId": 130140,
    "episodeMasterId": 130141,
    "episodeOrder": "First",
    "requiredCharacterLevel": 1
  },
  {
    "id": 130142,
    "characterMasterId": 130140,
    "episodeMasterId": 130142,
    "episodeOrder": "Second",
    "requiredCharacterLevel": 25
  },
  {
    "id": 130151,
    "characterMasterId": 130150,
    "episodeMasterId": 130151,
    "episodeOrder": "First",
    "requiredCharacterLevel": 1
  },
  {
    "id": 130152,
    "characterMasterId": 130150,
    "episodeMasterId": 130152,
    "episodeOrder": "Second",
    "requiredCharacterLevel": 25
  },
  {
    "id": 130161,
    "characterMasterId": 130160,
    "episodeMasterId": 130161,
    "episodeOrder": "First",
    "requiredCharacterLevel": 1
  },
  {
    "id": 130162,
    "characterMasterId": 130160,
    "episodeMasterId": 130162,
    "episodeOrder": "Second",
    "requiredCharacterLevel": 25
  },
  {
    "id": 130171,
    "characterMasterId": 130170,
    "episodeMasterId": 130171,
    "episodeOrder": "First",
    "requiredCharacterLevel": 1
  },
  {
    "id": 130172,
    "characterMasterId": 130170,
    "episodeMasterId": 130172,
    "episodeOrder": "Second",
    "requiredCharacterLevel": 25
  },
  {
    "id": 130181,
    "characterMasterId": 130180,
    "episodeMasterId": 130181,
    "episodeOrder": "First",
    "requiredCharacterLevel": 1
  },
  {
    "id": 130182,
    "characterMasterId": 130180,
    "episodeMasterId": 130182,
    "episodeOrder": "Second",
    "requiredCharacterLevel": 25
  },
  {
    "id": 130191,
    "characterMasterId": 130190,
    "episodeMasterId": 130191,
    "episodeOrder": "First",
    "requiredCharacterLevel": 1
  },
  {
    "id": 130192,
    "characterMasterId": 130190,
    "episodeMasterId": 130192,
    "episodeOrder": "Second",
    "requiredCharacterLevel": 25
  },
  {
    "id": 130201,
    "characterMasterId": 130200,
    "episodeMasterId": 130201,
    "episodeOrder": "First",
    "requiredCharacterLevel": 1
  },
  {
    "id": 130202,
    "characterMasterId": 130200,
    "episodeMasterId": 130202,
    "episodeOrder": "Second",
    "requiredCharacterLevel": 25
  },
  {
    "id": 130211,
    "characterMasterId": 130210,
    "episodeMasterId": 130211,
    "episodeOrder": "First",
    "requiredCharacterLevel": 1
  },
  {
    "id": 130212,
    "characterMasterId": 130210,
    "episodeMasterId": 130212,
    "episodeOrder": "Second",
    "requiredCharacterLevel": 25
  },
  {
    "id": 130221,
    "characterMasterId": 130220,
    "episodeMasterId": 130221,
    "episodeOrder": "First",
    "requiredCharacterLevel": 1
  },
  {
    "id": 130222,
    "characterMasterId": 130220,
    "episodeMasterId": 130222,
    "episodeOrder": "Second",
    "requiredCharacterLevel": 25
  },
  {
    "id": 130231,
    "characterMasterId": 130230,
    "episodeMasterId": 130231,
    "episodeOrder": "First",
    "requiredCharacterLevel": 1
  },
  {
    "id": 130232,
    "characterMasterId": 130230,
    "episodeMasterId": 130232,
    "episodeOrder": "Second",
    "requiredCharacterLevel": 25
  },
  {
    "id": 130241,
    "characterMasterId": 130240,
    "episodeMasterId": 130241,
    "episodeOrder": "First",
    "requiredCharacterLevel": 1
  },
  {
    "id": 130242,
    "characterMasterId": 130240,
    "episodeMasterId": 130242,
    "episodeOrder": "Second",
    "requiredCharacterLevel": 25
  },
  {
    "id": 130251,
    "characterMasterId": 130250,
    "episodeMasterId": 130251,
    "episodeOrder": "First",
    "requiredCharacterLevel": 1
  },
  {
    "id": 130252,
    "characterMasterId": 130250,
    "episodeMasterId": 130252,
    "episodeOrder": "Second",
    "requiredCharacterLevel": 25
  },
  {
    "id": 130261,
    "characterMasterId": 130260,
    "episodeMasterId": 130261,
    "episodeOrder": "First",
    "requiredCharacterLevel": 1
  },
  {
    "id": 130262,
    "characterMasterId": 130260,
    "episodeMasterId": 130262,
    "episodeOrder": "Second",
    "requiredCharacterLevel": 25
  },
  {
    "id": 130271,
    "characterMasterId": 130270,
    "episodeMasterId": 130271,
    "episodeOrder": "First",
    "requiredCharacterLevel": 1
  },
  {
    "id": 130272,
    "characterMasterId": 130270,
    "episodeMasterId": 130272,
    "episodeOrder": "Second",
    "requiredCharacterLevel": 25
  },
  {
    "id": 130281,
    "characterMasterId": 130280,
    "episodeMasterId": 130281,
    "episodeOrder": "First",
    "requiredCharacterLevel": 1
  },
  {
    "id": 130282,
    "characterMasterId": 130280,
    "episodeMasterId": 130282,
    "episodeOrder": "Second",
    "requiredCharacterLevel": 25
  },
  {
    "id": 130291,
    "characterMasterId": 130290,
    "episodeMasterId": 130291,
    "episodeOrder": "First",
    "requiredCharacterLevel": 1
  },
  {
    "id": 130292,
    "characterMasterId": 130290,
    "episodeMasterId": 130292,
    "episodeOrder": "Second",
    "requiredCharacterLevel": 25
  },
  {
    "id": 130301,
    "characterMasterId": 130300,
    "episodeMasterId": 130301,
    "episodeOrder": "First",
    "requiredCharacterLevel": 1
  },
  {
    "id": 130302,
    "characterMasterId": 130300,
    "episodeMasterId": 130302,
    "episodeOrder": "Second",
    "requiredCharacterLevel": 25
  },
  {
    "id": 130311,
    "characterMasterId": 130310,
    "episodeMasterId": 130311,
    "episodeOrder": "First",
    "requiredCharacterLevel": 1
  },
  {
    "id": 130312,
    "characterMasterId": 130310,
    "episodeMasterId": 130312,
    "episodeOrder": "Second",
    "requiredCharacterLevel": 25
  },
  {
    "id": 130321,
    "characterMasterId": 130320,
    "episodeMasterId": 130321,
    "episodeOrder": "First",
    "requiredCharacterLevel": 1
  },
  {
    "id": 130322,
    "characterMasterId": 130320,
    "episodeMasterId": 130322,
    "episodeOrder": "Second",
    "requiredCharacterLevel": 25
  },
  {
    "id": 130331,
    "characterMasterId": 130330,
    "episodeMasterId": 130331,
    "episodeOrder": "First",
    "requiredCharacterLevel": 1
  },
  {
    "id": 130332,
    "characterMasterId": 130330,
    "episodeMasterId": 130332,
    "episodeOrder": "Second",
    "requiredCharacterLevel": 25
  },
  {
    "id": 130341,
    "characterMasterId": 130340,
    "episodeMasterId": 130341,
    "episodeOrder": "First",
    "requiredCharacterLevel": 1
  },
  {
    "id": 130342,
    "characterMasterId": 130340,
    "episodeMasterId": 130342,
    "episodeOrder": "Second",
    "requiredCharacterLevel": 25
  },
  {
    "id": 130351,
    "characterMasterId": 130350,
    "episodeMasterId": 130351,
    "episodeOrder": "First",
    "requiredCharacterLevel": 1
  },
  {
    "id": 130352,
    "characterMasterId": 130350,
    "episodeMasterId": 130352,
    "episodeOrder": "Second",
    "requiredCharacterLevel": 25
  },
  {
    "id": 130361,
    "characterMasterId": 130360,
    "episodeMasterId": 130361,
    "episodeOrder": "First",
    "requiredCharacterLevel": 1
  },
  {
    "id": 130362,
    "characterMasterId": 130360,
    "episodeMasterId": 130362,
    "episodeOrder": "Second",
    "requiredCharacterLevel": 25
  },
  {
    "id": 130371,
    "characterMasterId": 130370,
    "episodeMasterId": 130371,
    "episodeOrder": "First",
    "requiredCharacterLevel": 1
  },
  {
    "id": 130372,
    "characterMasterId": 130370,
    "episodeMasterId": 130372,
    "episodeOrder": "Second",
    "requiredCharacterLevel": 25
  },
  {
    "id": 130381,
    "characterMasterId": 130380,
    "episodeMasterId": 130381,
    "episodeOrder": "First",
    "requiredCharacterLevel": 1
  },
  {
    "id": 130382,
    "characterMasterId": 130380,
    "episodeMasterId": 130382,
    "episodeOrder": "Second",
    "requiredCharacterLevel": 25
  },
  {
    "id": 130391,
    "characterMasterId": 130390,
    "episodeMasterId": 130391,
    "episodeOrder": "First",
    "requiredCharacterLevel": 1
  },
  {
    "id": 130392,
    "characterMasterId": 130390,
    "episodeMasterId": 130392,
    "episodeOrder": "Second",
    "requiredCharacterLevel": 25
  },
  {
    "id": 130401,
    "characterMasterId": 130400,
    "episodeMasterId": 130401,
    "episodeOrder": "First",
    "requiredCharacterLevel": 1
  },
  {
    "id": 130402,
    "characterMasterId": 130400,
    "episodeMasterId": 130402,
    "episodeOrder": "Second",
    "requiredCharacterLevel": 25
  },
  {
    "id": 130421,
    "characterMasterId": 130420,
    "episodeMasterId": 130421,
    "episodeOrder": "First",
    "requiredCharacterLevel": 1
  },
  {
    "id": 130422,
    "characterMasterId": 130420,
    "episodeMasterId": 130422,
    "episodeOrder": "Second",
    "requiredCharacterLevel": 25
  },
  {
    "id": 130431,
    "characterMasterId": 130430,
    "episodeMasterId": 130431,
    "episodeOrder": "First",
    "requiredCharacterLevel": 1
  },
  {
    "id": 130432,
    "characterMasterId": 130430,
    "episodeMasterId": 130432,
    "episodeOrder": "Second",
    "requiredCharacterLevel": 25
  },
  {
    "id": 130451,
    "characterMasterId": 130450,
    "episodeMasterId": 130451,
    "episodeOrder": "First",
    "requiredCharacterLevel": 1
  },
  {
    "id": 130452,
    "characterMasterId": 130450,
    "episodeMasterId": 130452,
    "episodeOrder": "Second",
    "requiredCharacterLevel": 25
  },
  {
    "id": 130461,
    "characterMasterId": 130460,
    "episodeMasterId": 130461,
    "episodeOrder": "First",
    "requiredCharacterLevel": 1
  },
  {
    "id": 130462,
    "characterMasterId": 130460,
    "episodeMasterId": 130462,
    "episodeOrder": "Second",
    "requiredCharacterLevel": 25
  },
  {
    "id": 130471,
    "characterMasterId": 130470,
    "episodeMasterId": 130471,
    "episodeOrder": "First",
    "requiredCharacterLevel": 1
  },
  {
    "id": 130472,
    "characterMasterId": 130470,
    "episodeMasterId": 130472,
    "episodeOrder": "Second",
    "requiredCharacterLevel": 25
  },
  {
    "id": 130481,
    "characterMasterId": 130480,
    "episodeMasterId": 130481,
    "episodeOrder": "First",
    "requiredCharacterLevel": 1
  },
  {
    "id": 130482,
    "characterMasterId": 130480,
    "episodeMasterId": 130482,
    "episodeOrder": "Second",
    "requiredCharacterLevel": 25
  },
  {
    "id": 130491,
    "characterMasterId": 130490,
    "episodeMasterId": 130491,
    "episodeOrder": "First",
    "requiredCharacterLevel": 1
  },
  {
    "id": 130492,
    "characterMasterId": 130490,
    "episodeMasterId": 130492,
    "episodeOrder": "Second",
    "requiredCharacterLevel": 25
  },
  {
    "id": 130501,
    "characterMasterId": 130500,
    "episodeMasterId": 130501,
    "episodeOrder": "First",
    "requiredCharacterLevel": 1
  },
  {
    "id": 130502,
    "characterMasterId": 130500,
    "episodeMasterId": 130502,
    "episodeOrder": "Second",
    "requiredCharacterLevel": 25
  },
  {
    "id": 130511,
    "characterMasterId": 130510,
    "episodeMasterId": 130511,
    "episodeOrder": "First",
    "requiredCharacterLevel": 1
  },
  {
    "id": 130512,
    "characterMasterId": 130510,
    "episodeMasterId": 130512,
    "episodeOrder": "Second",
    "requiredCharacterLevel": 25
  },
  {
    "id": 130521,
    "characterMasterId": 130520,
    "episodeMasterId": 130521,
    "episodeOrder": "First",
    "requiredCharacterLevel": 1
  },
  {
    "id": 130522,
    "characterMasterId": 130520,
    "episodeMasterId": 130522,
    "episodeOrder": "Second",
    "requiredCharacterLevel": 25
  },
  {
    "id": 130531,
    "characterMasterId": 130530,
    "episodeMasterId": 130531,
    "episodeOrder": "First",
    "requiredCharacterLevel": 1
  },
  {
    "id": 130532,
    "characterMasterId": 130530,
    "episodeMasterId": 130532,
    "episodeOrder": "Second",
    "requiredCharacterLevel": 25
  },
  {
    "id": 130541,
    "characterMasterId": 130540,
    "episodeMasterId": 130541,
    "episodeOrder": "First",
    "requiredCharacterLevel": 1
  },
  {
    "id": 130542,
    "characterMasterId": 130540,
    "episodeMasterId": 130542,
    "episodeOrder": "Second",
    "requiredCharacterLevel": 25
  },
  {
    "id": 130551,
    "characterMasterId": 130550,
    "episodeMasterId": 130551,
    "episodeOrder": "First",
    "requiredCharacterLevel": 1
  },
  {
    "id": 130552,
    "characterMasterId": 130550,
    "episodeMasterId": 130552,
    "episodeOrder": "Second",
    "requiredCharacterLevel": 25
  },
  {
    "id": 130561,
    "characterMasterId": 130560,
    "episodeMasterId": 130561,
    "episodeOrder": "First",
    "requiredCharacterLevel": 1
  },
  {
    "id": 130562,
    "characterMasterId": 130560,
    "episodeMasterId": 130562,
    "episodeOrder": "Second",
    "requiredCharacterLevel": 25
  },
  {
    "id": 130571,
    "characterMasterId": 130570,
    "episodeMasterId": 130571,
    "episodeOrder": "First",
    "requiredCharacterLevel": 1
  },
  {
    "id": 130572,
    "characterMasterId": 130570,
    "episodeMasterId": 130572,
    "episodeOrder": "Second",
    "requiredCharacterLevel": 25
  },
  {
    "id": 130581,
    "characterMasterId": 130580,
    "episodeMasterId": 130581,
    "episodeOrder": "First",
    "requiredCharacterLevel": 1
  },
  {
    "id": 130582,
    "characterMasterId": 130580,
    "episodeMasterId": 130582,
    "episodeOrder": "Second",
    "requiredCharacterLevel": 25
  },
  {
    "id": 130591,
    "characterMasterId": 130590,
    "episodeMasterId": 130591,
    "episodeOrder": "First",
    "requiredCharacterLevel": 1
  },
  {
    "id": 130592,
    "characterMasterId": 130590,
    "episodeMasterId": 130592,
    "episodeOrder": "Second",
    "requiredCharacterLevel": 25
  },
  {
    "id": 130601,
    "characterMasterId": 130600,
    "episodeMasterId": 130601,
    "episodeOrder": "First",
    "requiredCharacterLevel": 1
  },
  {
    "id": 130602,
    "characterMasterId": 130600,
    "episodeMasterId": 130602,
    "episodeOrder": "Second",
    "requiredCharacterLevel": 25
  },
  {
    "id": 130611,
    "characterMasterId": 130610,
    "episodeMasterId": 130611,
    "episodeOrder": "First",
    "requiredCharacterLevel": 1
  },
  {
    "id": 130612,
    "characterMasterId": 130610,
    "episodeMasterId": 130612,
    "episodeOrder": "Second",
    "requiredCharacterLevel": 25
  },
  {
    "id": 130621,
    "characterMasterId": 130620,
    "episodeMasterId": 130621,
    "episodeOrder": "First",
    "requiredCharacterLevel": 1
  },
  {
    "id": 130622,
    "characterMasterId": 130620,
    "episodeMasterId": 130622,
    "episodeOrder": "Second",
    "requiredCharacterLevel": 25
  },
  {
    "id": 130631,
    "characterMasterId": 130630,
    "episodeMasterId": 130631,
    "episodeOrder": "First",
    "requiredCharacterLevel": 1
  },
  {
    "id": 130632,
    "characterMasterId": 130630,
    "episodeMasterId": 130632,
    "episodeOrder": "Second",
    "requiredCharacterLevel": 25
  },
  {
    "id": 130641,
    "characterMasterId": 130640,
    "episodeMasterId": 130641,
    "episodeOrder": "First",
    "requiredCharacterLevel": 1
  },
  {
    "id": 130642,
    "characterMasterId": 130640,
    "episodeMasterId": 130642,
    "episodeOrder": "Second",
    "requiredCharacterLevel": 25
  },
  {
    "id": 130651,
    "characterMasterId": 130650,
    "episodeMasterId": 130651,
    "episodeOrder": "First",
    "requiredCharacterLevel": 1
  },
  {
    "id": 130652,
    "characterMasterId": 130650,
    "episodeMasterId": 130652,
    "episodeOrder": "Second",
    "requiredCharacterLevel": 25
  },
  {
    "id": 130661,
    "characterMasterId": 130660,
    "episodeMasterId": 130661,
    "episodeOrder": "First",
    "requiredCharacterLevel": 1
  },
  {
    "id": 130662,
    "characterMasterId": 130660,
    "episodeMasterId": 130662,
    "episodeOrder": "Second",
    "requiredCharacterLevel": 25
  },
  {
    "id": 130671,
    "characterMasterId": 130670,
    "episodeMasterId": 130671,
    "episodeOrder": "First",
    "requiredCharacterLevel": 1
  },
  {
    "id": 130672,
    "characterMasterId": 130670,
    "episodeMasterId": 130672,
    "episodeOrder": "Second",
    "requiredCharacterLevel": 25
  },
  {
    "id": 130681,
    "characterMasterId": 130680,
    "episodeMasterId": 130681,
    "episodeOrder": "First",
    "requiredCharacterLevel": 1
  },
  {
    "id": 130682,
    "characterMasterId": 130680,
    "episodeMasterId": 130682,
    "episodeOrder": "Second",
    "requiredCharacterLevel": 25
  },
  {
    "id": 130691,
    "characterMasterId": 130690,
    "episodeMasterId": 130691,
    "episodeOrder": "First",
    "requiredCharacterLevel": 1
  },
  {
    "id": 130692,
    "characterMasterId": 130690,
    "episodeMasterId": 130692,
    "episodeOrder": "Second",
    "requiredCharacterLevel": 25
  },
  {
    "id": 130701,
    "characterMasterId": 130700,
    "episodeMasterId": 130701,
    "episodeOrder": "First",
    "requiredCharacterLevel": 1
  },
  {
    "id": 130702,
    "characterMasterId": 130700,
    "episodeMasterId": 130702,
    "episodeOrder": "Second",
    "requiredCharacterLevel": 25
  },
  {
    "id": 130711,
    "characterMasterId": 130710,
    "episodeMasterId": 130711,
    "episodeOrder": "First",
    "requiredCharacterLevel": 1
  },
  {
    "id": 130712,
    "characterMasterId": 130710,
    "episodeMasterId": 130712,
    "episodeOrder": "Second",
    "requiredCharacterLevel": 25
  },
  {
    "id": 130721,
    "characterMasterId": 130720,
    "episodeMasterId": 130721,
    "episodeOrder": "First",
    "requiredCharacterLevel": 1
  },
  {
    "id": 130722,
    "characterMasterId": 130720,
    "episodeMasterId": 130722,
    "episodeOrder": "Second",
    "requiredCharacterLevel": 25
  },
  {
    "id": 130731,
    "characterMasterId": 130730,
    "episodeMasterId": 130731,
    "episodeOrder": "First",
    "requiredCharacterLevel": 1
  },
  {
    "id": 130732,
    "characterMasterId": 130730,
    "episodeMasterId": 130732,
    "episodeOrder": "Second",
    "requiredCharacterLevel": 25
  },
  {
    "id": 130741,
    "characterMasterId": 130740,
    "episodeMasterId": 130741,
    "episodeOrder": "First",
    "requiredCharacterLevel": 1
  },
  {
    "id": 130742,
    "characterMasterId": 130740,
    "episodeMasterId": 130742,
    "episodeOrder": "Second",
    "requiredCharacterLevel": 25
  },
  {
    "id": 130751,
    "characterMasterId": 130750,
    "episodeMasterId": 130751,
    "episodeOrder": "First",
    "requiredCharacterLevel": 1
  },
  {
    "id": 130752,
    "characterMasterId": 130750,
    "episodeMasterId": 130752,
    "episodeOrder": "Second",
    "requiredCharacterLevel": 25
  },
  {
    "id": 130761,
    "characterMasterId": 130760,
    "episodeMasterId": 130761,
    "episodeOrder": "First",
    "requiredCharacterLevel": 1
  },
  {
    "id": 130762,
    "characterMasterId": 130760,
    "episodeMasterId": 130762,
    "episodeOrder": "Second",
    "requiredCharacterLevel": 25
  },
  {
    "id": 130771,
    "characterMasterId": 130770,
    "episodeMasterId": 130771,
    "episodeOrder": "First",
    "requiredCharacterLevel": 1
  },
  {
    "id": 130772,
    "characterMasterId": 130770,
    "episodeMasterId": 130772,
    "episodeOrder": "Second",
    "requiredCharacterLevel": 25
  },
  {
    "id": 130781,
    "characterMasterId": 130780,
    "episodeMasterId": 130781,
    "episodeOrder": "First",
    "requiredCharacterLevel": 1
  },
  {
    "id": 130782,
    "characterMasterId": 130780,
    "episodeMasterId": 130782,
    "episodeOrder": "Second",
    "requiredCharacterLevel": 25
  },
  {
    "id": 130791,
    "characterMasterId": 130790,
    "episodeMasterId": 130791,
    "episodeOrder": "First",
    "requiredCharacterLevel": 1
  },
  {
    "id": 130792,
    "characterMasterId": 130790,
    "episodeMasterId": 130792,
    "episodeOrder": "Second",
    "requiredCharacterLevel": 25
  },
  {
    "id": 130801,
    "characterMasterId": 130800,
    "episodeMasterId": 130801,
    "episodeOrder": "First",
    "requiredCharacterLevel": 1
  },
  {
    "id": 130802,
    "characterMasterId": 130800,
    "episodeMasterId": 130802,
    "episodeOrder": "Second",
    "requiredCharacterLevel": 25
  },
  {
    "id": 130811,
    "characterMasterId": 130810,
    "episodeMasterId": 130811,
    "episodeOrder": "First",
    "requiredCharacterLevel": 1
  },
  {
    "id": 130812,
    "characterMasterId": 130810,
    "episodeMasterId": 130812,
    "episodeOrder": "Second",
    "requiredCharacterLevel": 25
  },
  {
    "id": 130821,
    "characterMasterId": 130820,
    "episodeMasterId": 130821,
    "episodeOrder": "First",
    "requiredCharacterLevel": 1
  },
  {
    "id": 130822,
    "characterMasterId": 130820,
    "episodeMasterId": 130822,
    "episodeOrder": "Second",
    "requiredCharacterLevel": 25
  },
  {
    "id": 130831,
    "characterMasterId": 130830,
    "episodeMasterId": 130831,
    "episodeOrder": "First",
    "requiredCharacterLevel": 1
  },
  {
    "id": 130832,
    "characterMasterId": 130830,
    "episodeMasterId": 130832,
    "episodeOrder": "Second",
    "requiredCharacterLevel": 25
  },
  {
    "id": 130841,
    "characterMasterId": 130840,
    "episodeMasterId": 130841,
    "episodeOrder": "First",
    "requiredCharacterLevel": 1
  },
  {
    "id": 130842,
    "characterMasterId": 130840,
    "episodeMasterId": 130842,
    "episodeOrder": "Second",
    "requiredCharacterLevel": 25
  },
  {
    "id": 140011,
    "characterMasterId": 140010,
    "episodeMasterId": 140011,
    "episodeOrder": "First",
    "requiredCharacterLevel": 1
  },
  {
    "id": 140012,
    "characterMasterId": 140010,
    "episodeMasterId": 140012,
    "episodeOrder": "Second",
    "requiredCharacterLevel": 25
  },
  {
    "id": 140021,
    "characterMasterId": 140020,
    "episodeMasterId": 140021,
    "episodeOrder": "First",
    "requiredCharacterLevel": 1
  },
  {
    "id": 140022,
    "characterMasterId": 140020,
    "episodeMasterId": 140022,
    "episodeOrder": "Second",
    "requiredCharacterLevel": 25
  },
  {
    "id": 140031,
    "characterMasterId": 140030,
    "episodeMasterId": 140031,
    "episodeOrder": "First",
    "requiredCharacterLevel": 1
  },
  {
    "id": 140032,
    "characterMasterId": 140030,
    "episodeMasterId": 140032,
    "episodeOrder": "Second",
    "requiredCharacterLevel": 25
  },
  {
    "id": 140041,
    "characterMasterId": 140040,
    "episodeMasterId": 140041,
    "episodeOrder": "First",
    "requiredCharacterLevel": 1
  },
  {
    "id": 140042,
    "characterMasterId": 140040,
    "episodeMasterId": 140042,
    "episodeOrder": "Second",
    "requiredCharacterLevel": 25
  },
  {
    "id": 140051,
    "characterMasterId": 140050,
    "episodeMasterId": 140051,
    "episodeOrder": "First",
    "requiredCharacterLevel": 1
  },
  {
    "id": 140052,
    "characterMasterId": 140050,
    "episodeMasterId": 140052,
    "episodeOrder": "Second",
    "requiredCharacterLevel": 25
  },
  {
    "id": 140061,
    "characterMasterId": 140060,
    "episodeMasterId": 140061,
    "episodeOrder": "First",
    "requiredCharacterLevel": 1
  },
  {
    "id": 140062,
    "characterMasterId": 140060,
    "episodeMasterId": 140062,
    "episodeOrder": "Second",
    "requiredCharacterLevel": 25
  },
  {
    "id": 140071,
    "characterMasterId": 140070,
    "episodeMasterId": 140071,
    "episodeOrder": "First",
    "requiredCharacterLevel": 1
  },
  {
    "id": 140072,
    "characterMasterId": 140070,
    "episodeMasterId": 140072,
    "episodeOrder": "Second",
    "requiredCharacterLevel": 25
  },
  {
    "id": 140081,
    "characterMasterId": 140080,
    "episodeMasterId": 140081,
    "episodeOrder": "First",
    "requiredCharacterLevel": 1
  },
  {
    "id": 140082,
    "characterMasterId": 140080,
    "episodeMasterId": 140082,
    "episodeOrder": "Second",
    "requiredCharacterLevel": 25
  },
  {
    "id": 140091,
    "characterMasterId": 140090,
    "episodeMasterId": 140091,
    "episodeOrder": "First",
    "requiredCharacterLevel": 1
  },
  {
    "id": 140092,
    "characterMasterId": 140090,
    "episodeMasterId": 140092,
    "episodeOrder": "Second",
    "requiredCharacterLevel": 25
  },
  {
    "id": 140101,
    "characterMasterId": 140100,
    "episodeMasterId": 140101,
    "episodeOrder": "First",
    "requiredCharacterLevel": 1
  },
  {
    "id": 140102,
    "characterMasterId": 140100,
    "episodeMasterId": 140102,
    "episodeOrder": "Second",
    "requiredCharacterLevel": 25
  },
  {
    "id": 140111,
    "characterMasterId": 140110,
    "episodeMasterId": 140111,
    "episodeOrder": "First",
    "requiredCharacterLevel": 1
  },
  {
    "id": 140112,
    "characterMasterId": 140110,
    "episodeMasterId": 140112,
    "episodeOrder": "Second",
    "requiredCharacterLevel": 25
  },
  {
    "id": 140121,
    "characterMasterId": 140120,
    "episodeMasterId": 140121,
    "episodeOrder": "First",
    "requiredCharacterLevel": 1
  },
  {
    "id": 140122,
    "characterMasterId": 140120,
    "episodeMasterId": 140122,
    "episodeOrder": "Second",
    "requiredCharacterLevel": 25
  },
  {
    "id": 140131,
    "characterMasterId": 140130,
    "episodeMasterId": 140131,
    "episodeOrder": "First",
    "requiredCharacterLevel": 1
  },
  {
    "id": 140132,
    "characterMasterId": 140130,
    "episodeMasterId": 140132,
    "episodeOrder": "Second",
    "requiredCharacterLevel": 25
  },
  {
    "id": 140141,
    "characterMasterId": 140140,
    "episodeMasterId": 140141,
    "episodeOrder": "First",
    "requiredCharacterLevel": 1
  },
  {
    "id": 140142,
    "characterMasterId": 140140,
    "episodeMasterId": 140142,
    "episodeOrder": "Second",
    "requiredCharacterLevel": 25
  },
  {
    "id": 140151,
    "characterMasterId": 140150,
    "episodeMasterId": 140151,
    "episodeOrder": "First",
    "requiredCharacterLevel": 1
  },
  {
    "id": 140152,
    "characterMasterId": 140150,
    "episodeMasterId": 140152,
    "episodeOrder": "Second",
    "requiredCharacterLevel": 25
  },
  {
    "id": 140161,
    "characterMasterId": 140160,
    "episodeMasterId": 140161,
    "episodeOrder": "First",
    "requiredCharacterLevel": 1
  },
  {
    "id": 140162,
    "characterMasterId": 140160,
    "episodeMasterId": 140162,
    "episodeOrder": "Second",
    "requiredCharacterLevel": 25
  },
  {
    "id": 140171,
    "characterMasterId": 140170,
    "episodeMasterId": 140171,
    "episodeOrder": "First",
    "requiredCharacterLevel": 1
  },
  {
    "id": 140172,
    "characterMasterId": 140170,
    "episodeMasterId": 140172,
    "episodeOrder": "Second",
    "requiredCharacterLevel": 25
  },
  {
    "id": 140181,
    "characterMasterId": 140180,
    "episodeMasterId": 140181,
    "episodeOrder": "First",
    "requiredCharacterLevel": 1
  },
  {
    "id": 140182,
    "characterMasterId": 140180,
    "episodeMasterId": 140182,
    "episodeOrder": "Second",
    "requiredCharacterLevel": 25
  },
  {
    "id": 140191,
    "characterMasterId": 140190,
    "episodeMasterId": 140191,
    "episodeOrder": "First",
    "requiredCharacterLevel": 1
  },
  {
    "id": 140192,
    "characterMasterId": 140190,
    "episodeMasterId": 140192,
    "episodeOrder": "Second",
    "requiredCharacterLevel": 25
  },
  {
    "id": 140201,
    "characterMasterId": 140200,
    "episodeMasterId": 140201,
    "episodeOrder": "First",
    "requiredCharacterLevel": 1
  },
  {
    "id": 140202,
    "characterMasterId": 140200,
    "episodeMasterId": 140202,
    "episodeOrder": "Second",
    "requiredCharacterLevel": 25
  },
  {
    "id": 140211,
    "characterMasterId": 140210,
    "episodeMasterId": 140211,
    "episodeOrder": "First",
    "requiredCharacterLevel": 1
  },
  {
    "id": 140212,
    "characterMasterId": 140210,
    "episodeMasterId": 140212,
    "episodeOrder": "Second",
    "requiredCharacterLevel": 25
  },
  {
    "id": 140221,
    "characterMasterId": 140220,
    "episodeMasterId": 140221,
    "episodeOrder": "First",
    "requiredCharacterLevel": 1
  },
  {
    "id": 140222,
    "characterMasterId": 140220,
    "episodeMasterId": 140222,
    "episodeOrder": "Second",
    "requiredCharacterLevel": 25
  },
  {
    "id": 140241,
    "characterMasterId": 140240,
    "episodeMasterId": 140241,
    "episodeOrder": "First",
    "requiredCharacterLevel": 1
  },
  {
    "id": 140242,
    "characterMasterId": 140240,
    "episodeMasterId": 140242,
    "episodeOrder": "Second",
    "requiredCharacterLevel": 25
  },
  {
    "id": 140251,
    "characterMasterId": 140250,
    "episodeMasterId": 140251,
    "episodeOrder": "First",
    "requiredCharacterLevel": 1
  },
  {
    "id": 140252,
    "characterMasterId": 140250,
    "episodeMasterId": 140252,
    "episodeOrder": "Second",
    "requiredCharacterLevel": 25
  },
  {
    "id": 140261,
    "characterMasterId": 140260,
    "episodeMasterId": 140261,
    "episodeOrder": "First",
    "requiredCharacterLevel": 1
  },
  {
    "id": 140262,
    "characterMasterId": 140260,
    "episodeMasterId": 140262,
    "episodeOrder": "Second",
    "requiredCharacterLevel": 25
  },
  {
    "id": 140271,
    "characterMasterId": 140270,
    "episodeMasterId": 140271,
    "episodeOrder": "First",
    "requiredCharacterLevel": 1
  },
  {
    "id": 140272,
    "characterMasterId": 140270,
    "episodeMasterId": 140272,
    "episodeOrder": "Second",
    "requiredCharacterLevel": 25
  },
  {
    "id": 140281,
    "characterMasterId": 140280,
    "episodeMasterId": 140281,
    "episodeOrder": "First",
    "requiredCharacterLevel": 1
  },
  {
    "id": 140282,
    "characterMasterId": 140280,
    "episodeMasterId": 140282,
    "episodeOrder": "Second",
    "requiredCharacterLevel": 25
  },
  {
    "id": 140291,
    "characterMasterId": 140290,
    "episodeMasterId": 140291,
    "episodeOrder": "First",
    "requiredCharacterLevel": 1
  },
  {
    "id": 140292,
    "characterMasterId": 140290,
    "episodeMasterId": 140292,
    "episodeOrder": "Second",
    "requiredCharacterLevel": 25
  },
  {
    "id": 140301,
    "characterMasterId": 140300,
    "episodeMasterId": 140301,
    "episodeOrder": "First",
    "requiredCharacterLevel": 1
  },
  {
    "id": 140302,
    "characterMasterId": 140300,
    "episodeMasterId": 140302,
    "episodeOrder": "Second",
    "requiredCharacterLevel": 25
  },
  {
    "id": 140311,
    "characterMasterId": 140310,
    "episodeMasterId": 140311,
    "episodeOrder": "First",
    "requiredCharacterLevel": 1
  },
  {
    "id": 140312,
    "characterMasterId": 140310,
    "episodeMasterId": 140312,
    "episodeOrder": "Second",
    "requiredCharacterLevel": 25
  },
  {
    "id": 140321,
    "characterMasterId": 140320,
    "episodeMasterId": 140321,
    "episodeOrder": "First",
    "requiredCharacterLevel": 1
  },
  {
    "id": 140322,
    "characterMasterId": 140320,
    "episodeMasterId": 140322,
    "episodeOrder": "Second",
    "requiredCharacterLevel": 25
  },
  {
    "id": 140331,
    "characterMasterId": 140330,
    "episodeMasterId": 140331,
    "episodeOrder": "First",
    "requiredCharacterLevel": 1
  },
  {
    "id": 140332,
    "characterMasterId": 140330,
    "episodeMasterId": 140332,
    "episodeOrder": "Second",
    "requiredCharacterLevel": 25
  },
  {
    "id": 140341,
    "characterMasterId": 140340,
    "episodeMasterId": 140341,
    "episodeOrder": "First",
    "requiredCharacterLevel": 1
  },
  {
    "id": 140342,
    "characterMasterId": 140340,
    "episodeMasterId": 140342,
    "episodeOrder": "Second",
    "requiredCharacterLevel": 25
  },
  {
    "id": 140351,
    "characterMasterId": 140350,
    "episodeMasterId": 140351,
    "episodeOrder": "First",
    "requiredCharacterLevel": 1
  },
  {
    "id": 140352,
    "characterMasterId": 140350,
    "episodeMasterId": 140352,
    "episodeOrder": "Second",
    "requiredCharacterLevel": 25
  },
  {
    "id": 140361,
    "characterMasterId": 140360,
    "episodeMasterId": 140361,
    "episodeOrder": "First",
    "requiredCharacterLevel": 1
  },
  {
    "id": 140362,
    "characterMasterId": 140360,
    "episodeMasterId": 140362,
    "episodeOrder": "Second",
    "requiredCharacterLevel": 25
  },
  {
    "id": 140371,
    "characterMasterId": 140370,
    "episodeMasterId": 140371,
    "episodeOrder": "First",
    "requiredCharacterLevel": 1
  },
  {
    "id": 140372,
    "characterMasterId": 140370,
    "episodeMasterId": 140372,
    "episodeOrder": "Second",
    "requiredCharacterLevel": 25
  },
  {
    "id": 140381,
    "characterMasterId": 140380,
    "episodeMasterId": 140381,
    "episodeOrder": "First",
    "requiredCharacterLevel": 1
  },
  {
    "id": 140382,
    "characterMasterId": 140380,
    "episodeMasterId": 140382,
    "episodeOrder": "Second",
    "requiredCharacterLevel": 25
  },
  {
    "id": 140391,
    "characterMasterId": 140390,
    "episodeMasterId": 140391,
    "episodeOrder": "First",
    "requiredCharacterLevel": 1
  },
  {
    "id": 140392,
    "characterMasterId": 140390,
    "episodeMasterId": 140392,
    "episodeOrder": "Second",
    "requiredCharacterLevel": 25
  },
  {
    "id": 140401,
    "characterMasterId": 140400,
    "episodeMasterId": 140401,
    "episodeOrder": "First",
    "requiredCharacterLevel": 1
  },
  {
    "id": 140402,
    "characterMasterId": 140400,
    "episodeMasterId": 140402,
    "episodeOrder": "Second",
    "requiredCharacterLevel": 25
  },
  {
    "id": 140411,
    "characterMasterId": 140410,
    "episodeMasterId": 140411,
    "episodeOrder": "First",
    "requiredCharacterLevel": 1
  },
  {
    "id": 140412,
    "characterMasterId": 140410,
    "episodeMasterId": 140412,
    "episodeOrder": "Second",
    "requiredCharacterLevel": 25
  },
  {
    "id": 140421,
    "characterMasterId": 140420,
    "episodeMasterId": 140421,
    "episodeOrder": "First",
    "requiredCharacterLevel": 1
  },
  {
    "id": 140422,
    "characterMasterId": 140420,
    "episodeMasterId": 140422,
    "episodeOrder": "Second",
    "requiredCharacterLevel": 25
  },
  {
    "id": 140431,
    "characterMasterId": 140430,
    "episodeMasterId": 140431,
    "episodeOrder": "First",
    "requiredCharacterLevel": 1
  },
  {
    "id": 140432,
    "characterMasterId": 140430,
    "episodeMasterId": 140432,
    "episodeOrder": "Second",
    "requiredCharacterLevel": 25
  },
  {
    "id": 140441,
    "characterMasterId": 140440,
    "episodeMasterId": 140441,
    "episodeOrder": "First",
    "requiredCharacterLevel": 1
  },
  {
    "id": 140442,
    "characterMasterId": 140440,
    "episodeMasterId": 140442,
    "episodeOrder": "Second",
    "requiredCharacterLevel": 25
  },
  {
    "id": 140451,
    "characterMasterId": 140450,
    "episodeMasterId": 140451,
    "episodeOrder": "First",
    "requiredCharacterLevel": 1
  },
  {
    "id": 140452,
    "characterMasterId": 140450,
    "episodeMasterId": 140452,
    "episodeOrder": "Second",
    "requiredCharacterLevel": 25
  },
  {
    "id": 140461,
    "characterMasterId": 140460,
    "episodeMasterId": 140461,
    "episodeOrder": "First",
    "requiredCharacterLevel": 1
  },
  {
    "id": 140462,
    "characterMasterId": 140460,
    "episodeMasterId": 140462,
    "episodeOrder": "Second",
    "requiredCharacterLevel": 25
  },
  {
    "id": 140471,
    "characterMasterId": 140470,
    "episodeMasterId": 140471,
    "episodeOrder": "First",
    "requiredCharacterLevel": 1
  },
  {
    "id": 140472,
    "characterMasterId": 140470,
    "episodeMasterId": 140472,
    "episodeOrder": "Second",
    "requiredCharacterLevel": 25
  },
  {
    "id": 140481,
    "characterMasterId": 140480,
    "episodeMasterId": 140481,
    "episodeOrder": "First",
    "requiredCharacterLevel": 1
  },
  {
    "id": 140482,
    "characterMasterId": 140480,
    "episodeMasterId": 140482,
    "episodeOrder": "Second",
    "requiredCharacterLevel": 25
  },
  {
    "id": 140491,
    "characterMasterId": 140490,
    "episodeMasterId": 140491,
    "episodeOrder": "First",
    "requiredCharacterLevel": 1
  },
  {
    "id": 140492,
    "characterMasterId": 140490,
    "episodeMasterId": 140492,
    "episodeOrder": "Second",
    "requiredCharacterLevel": 25
  },
  {
    "id": 140501,
    "characterMasterId": 140500,
    "episodeMasterId": 140501,
    "episodeOrder": "First",
    "requiredCharacterLevel": 1
  },
  {
    "id": 140502,
    "characterMasterId": 140500,
    "episodeMasterId": 140502,
    "episodeOrder": "Second",
    "requiredCharacterLevel": 25
  },
  {
    "id": 140511,
    "characterMasterId": 140510,
    "episodeMasterId": 140511,
    "episodeOrder": "First",
    "requiredCharacterLevel": 1
  },
  {
    "id": 140512,
    "characterMasterId": 140510,
    "episodeMasterId": 140512,
    "episodeOrder": "Second",
    "requiredCharacterLevel": 25
  },
  {
    "id": 140521,
    "characterMasterId": 140520,
    "episodeMasterId": 140521,
    "episodeOrder": "First",
    "requiredCharacterLevel": 1
  },
  {
    "id": 140522,
    "characterMasterId": 140520,
    "episodeMasterId": 140522,
    "episodeOrder": "Second",
    "requiredCharacterLevel": 25
  },
  {
    "id": 140531,
    "characterMasterId": 140530,
    "episodeMasterId": 140531,
    "episodeOrder": "First",
    "requiredCharacterLevel": 1
  },
  {
    "id": 140532,
    "characterMasterId": 140530,
    "episodeMasterId": 140532,
    "episodeOrder": "Second",
    "requiredCharacterLevel": 25
  },
  {
    "id": 140541,
    "characterMasterId": 140540,
    "episodeMasterId": 140541,
    "episodeOrder": "First",
    "requiredCharacterLevel": 1
  },
  {
    "id": 140542,
    "characterMasterId": 140540,
    "episodeMasterId": 140542,
    "episodeOrder": "Second",
    "requiredCharacterLevel": 25
  },
  {
    "id": 140551,
    "characterMasterId": 140550,
    "episodeMasterId": 140551,
    "episodeOrder": "First",
    "requiredCharacterLevel": 1
  },
  {
    "id": 140552,
    "characterMasterId": 140550,
    "episodeMasterId": 140552,
    "episodeOrder": "Second",
    "requiredCharacterLevel": 25
  },
  {
    "id": 140561,
    "characterMasterId": 140560,
    "episodeMasterId": 140561,
    "episodeOrder": "First",
    "requiredCharacterLevel": 1
  },
  {
    "id": 140562,
    "characterMasterId": 140560,
    "episodeMasterId": 140562,
    "episodeOrder": "Second",
    "requiredCharacterLevel": 25
  },
  {
    "id": 140571,
    "characterMasterId": 140570,
    "episodeMasterId": 140571,
    "episodeOrder": "First",
    "requiredCharacterLevel": 1
  },
  {
    "id": 140572,
    "characterMasterId": 140570,
    "episodeMasterId": 140572,
    "episodeOrder": "Second",
    "requiredCharacterLevel": 25
  },
  {
    "id": 140601,
    "characterMasterId": 140600,
    "episodeMasterId": 140601,
    "episodeOrder": "First",
    "requiredCharacterLevel": 1
  },
  {
    "id": 140602,
    "characterMasterId": 140600,
    "episodeMasterId": 140602,
    "episodeOrder": "Second",
    "requiredCharacterLevel": 25
  },
  {
    "id": 140611,
    "characterMasterId": 140610,
    "episodeMasterId": 140611,
    "episodeOrder": "First",
    "requiredCharacterLevel": 1
  },
  {
    "id": 140612,
    "characterMasterId": 140610,
    "episodeMasterId": 140612,
    "episodeOrder": "Second",
    "requiredCharacterLevel": 25
  },
  {
    "id": 140621,
    "characterMasterId": 140620,
    "episodeMasterId": 140621,
    "episodeOrder": "First",
    "requiredCharacterLevel": 1
  },
  {
    "id": 140622,
    "characterMasterId": 140620,
    "episodeMasterId": 140622,
    "episodeOrder": "Second",
    "requiredCharacterLevel": 25
  },
  {
    "id": 140631,
    "characterMasterId": 140630,
    "episodeMasterId": 140631,
    "episodeOrder": "First",
    "requiredCharacterLevel": 1
  },
  {
    "id": 140632,
    "characterMasterId": 140630,
    "episodeMasterId": 140632,
    "episodeOrder": "Second",
    "requiredCharacterLevel": 25
  },
  {
    "id": 140661,
    "characterMasterId": 140660,
    "episodeMasterId": 140661,
    "episodeOrder": "First",
    "requiredCharacterLevel": 1
  },
  {
    "id": 140662,
    "characterMasterId": 140660,
    "episodeMasterId": 140662,
    "episodeOrder": "Second",
    "requiredCharacterLevel": 25
  },
  {
    "id": 140671,
    "characterMasterId": 140670,
    "episodeMasterId": 140671,
    "episodeOrder": "First",
    "requiredCharacterLevel": 1
  },
  {
    "id": 140672,
    "characterMasterId": 140670,
    "episodeMasterId": 140672,
    "episodeOrder": "Second",
    "requiredCharacterLevel": 25
  },
  {
    "id": 140681,
    "characterMasterId": 140680,
    "episodeMasterId": 140681,
    "episodeOrder": "First",
    "requiredCharacterLevel": 1
  },
  {
    "id": 140682,
    "characterMasterId": 140680,
    "episodeMasterId": 140682,
    "episodeOrder": "Second",
    "requiredCharacterLevel": 25
  },
  {
    "id": 140691,
    "characterMasterId": 140690,
    "episodeMasterId": 140691,
    "episodeOrder": "First",
    "requiredCharacterLevel": 1
  },
  {
    "id": 140692,
    "characterMasterId": 140690,
    "episodeMasterId": 140692,
    "episodeOrder": "Second",
    "requiredCharacterLevel": 25
  },
  {
    "id": 140701,
    "characterMasterId": 140700,
    "episodeMasterId": 140701,
    "episodeOrder": "First",
    "requiredCharacterLevel": 1
  },
  {
    "id": 140702,
    "characterMasterId": 140700,
    "episodeMasterId": 140702,
    "episodeOrder": "Second",
    "requiredCharacterLevel": 25
  },
  {
    "id": 140711,
    "characterMasterId": 140710,
    "episodeMasterId": 140711,
    "episodeOrder": "First",
    "requiredCharacterLevel": 1
  },
  {
    "id": 140712,
    "characterMasterId": 140710,
    "episodeMasterId": 140712,
    "episodeOrder": "Second",
    "requiredCharacterLevel": 25
  },
  {
    "id": 140721,
    "characterMasterId": 140720,
    "episodeMasterId": 140721,
    "episodeOrder": "First",
    "requiredCharacterLevel": 1
  },
  {
    "id": 140722,
    "characterMasterId": 140720,
    "episodeMasterId": 140722,
    "episodeOrder": "Second",
    "requiredCharacterLevel": 25
  },
  {
    "id": 140731,
    "characterMasterId": 140730,
    "episodeMasterId": 140731,
    "episodeOrder": "First",
    "requiredCharacterLevel": 1
  },
  {
    "id": 140732,
    "characterMasterId": 140730,
    "episodeMasterId": 140732,
    "episodeOrder": "Second",
    "requiredCharacterLevel": 25
  },
  {
    "id": 140741,
    "characterMasterId": 140740,
    "episodeMasterId": 140741,
    "episodeOrder": "First",
    "requiredCharacterLevel": 1
  },
  {
    "id": 140742,
    "characterMasterId": 140740,
    "episodeMasterId": 140742,
    "episodeOrder": "Second",
    "requiredCharacterLevel": 25
  },
  {
    "id": 140751,
    "characterMasterId": 140750,
    "episodeMasterId": 140751,
    "episodeOrder": "First",
    "requiredCharacterLevel": 1
  },
  {
    "id": 140752,
    "characterMasterId": 140750,
    "episodeMasterId": 140752,
    "episodeOrder": "Second",
    "requiredCharacterLevel": 25
  },
  {
    "id": 140761,
    "characterMasterId": 140760,
    "episodeMasterId": 140761,
    "episodeOrder": "First",
    "requiredCharacterLevel": 1
  },
  {
    "id": 140762,
    "characterMasterId": 140760,
    "episodeMasterId": 140762,
    "episodeOrder": "Second",
    "requiredCharacterLevel": 25
  },
  {
    "id": 140771,
    "characterMasterId": 140770,
    "episodeMasterId": 140771,
    "episodeOrder": "First",
    "requiredCharacterLevel": 1
  },
  {
    "id": 140772,
    "characterMasterId": 140770,
    "episodeMasterId": 140772,
    "episodeOrder": "Second",
    "requiredCharacterLevel": 25
  },
  {
    "id": 140781,
    "characterMasterId": 140780,
    "episodeMasterId": 140781,
    "episodeOrder": "First",
    "requiredCharacterLevel": 1
  },
  {
    "id": 140782,
    "characterMasterId": 140780,
    "episodeMasterId": 140782,
    "episodeOrder": "Second",
    "requiredCharacterLevel": 25
  },
  {
    "id": 140791,
    "characterMasterId": 140790,
    "episodeMasterId": 140791,
    "episodeOrder": "First",
    "requiredCharacterLevel": 1
  },
  {
    "id": 140792,
    "characterMasterId": 140790,
    "episodeMasterId": 140792,
    "episodeOrder": "Second",
    "requiredCharacterLevel": 25
  },
  {
    "id": 140801,
    "characterMasterId": 140800,
    "episodeMasterId": 140801,
    "episodeOrder": "First",
    "requiredCharacterLevel": 1
  },
  {
    "id": 140802,
    "characterMasterId": 140800,
    "episodeMasterId": 140802,
    "episodeOrder": "Second",
    "requiredCharacterLevel": 25
  },
  {
    "id": 140811,
    "characterMasterId": 140810,
    "episodeMasterId": 140811,
    "episodeOrder": "First",
    "requiredCharacterLevel": 1
  },
  {
    "id": 140812,
    "characterMasterId": 140810,
    "episodeMasterId": 140812,
    "episodeOrder": "Second",
    "requiredCharacterLevel": 25
  },
  {
    "id": 140821,
    "characterMasterId": 140820,
    "episodeMasterId": 140821,
    "episodeOrder": "First",
    "requiredCharacterLevel": 1
  },
  {
    "id": 140822,
    "characterMasterId": 140820,
    "episodeMasterId": 140822,
    "episodeOrder": "Second",
    "requiredCharacterLevel": 25
  },
  {
    "id": 140831,
    "characterMasterId": 140830,
    "episodeMasterId": 140831,
    "episodeOrder": "First",
    "requiredCharacterLevel": 1
  },
  {
    "id": 140832,
    "characterMasterId": 140830,
    "episodeMasterId": 140832,
    "episodeOrder": "Second",
    "requiredCharacterLevel": 25
  },
  {
    "id": 140841,
    "characterMasterId": 140840,
    "episodeMasterId": 140841,
    "episodeOrder": "First",
    "requiredCharacterLevel": 1
  },
  {
    "id": 140842,
    "characterMasterId": 140840,
    "episodeMasterId": 140842,
    "episodeOrder": "Second",
    "requiredCharacterLevel": 25
  },
  {
    "id": 140851,
    "characterMasterId": 140850,
    "episodeMasterId": 140851,
    "episodeOrder": "First",
    "requiredCharacterLevel": 1
  },
  {
    "id": 140852,
    "characterMasterId": 140850,
    "episodeMasterId": 140852,
    "episodeOrder": "Second",
    "requiredCharacterLevel": 25
  },
  {
    "id": 140861,
    "characterMasterId": 140860,
    "episodeMasterId": 140861,
    "episodeOrder": "First",
    "requiredCharacterLevel": 1
  },
  {
    "id": 140862,
    "characterMasterId": 140860,
    "episodeMasterId": 140862,
    "episodeOrder": "Second",
    "requiredCharacterLevel": 25
  },
  {
    "id": 140871,
    "characterMasterId": 140870,
    "episodeMasterId": 140871,
    "episodeOrder": "First",
    "requiredCharacterLevel": 1
  },
  {
    "id": 140872,
    "characterMasterId": 140870,
    "episodeMasterId": 140872,
    "episodeOrder": "Second",
    "requiredCharacterLevel": 25
  },
  {
    "id": 140881,
    "characterMasterId": 140880,
    "episodeMasterId": 140881,
    "episodeOrder": "First",
    "requiredCharacterLevel": 1
  },
  {
    "id": 140882,
    "characterMasterId": 140880,
    "episodeMasterId": 140882,
    "episodeOrder": "Second",
    "requiredCharacterLevel": 25
  },
  {
    "id": 140891,
    "characterMasterId": 140890,
    "episodeMasterId": 140891,
    "episodeOrder": "First",
    "requiredCharacterLevel": 1
  },
  {
    "id": 140892,
    "characterMasterId": 140890,
    "episodeMasterId": 140892,
    "episodeOrder": "Second",
    "requiredCharacterLevel": 25
  },
  {
    "id": 140901,
    "characterMasterId": 140900,
    "episodeMasterId": 140901,
    "episodeOrder": "First",
    "requiredCharacterLevel": 1
  },
  {
    "id": 140902,
    "characterMasterId": 140900,
    "episodeMasterId": 140902,
    "episodeOrder": "Second",
    "requiredCharacterLevel": 25
  },
  {
    "id": 140911,
    "characterMasterId": 140910,
    "episodeMasterId": 140911,
    "episodeOrder": "First",
    "requiredCharacterLevel": 1
  },
  {
    "id": 140912,
    "characterMasterId": 140910,
    "episodeMasterId": 140912,
    "episodeOrder": "Second",
    "requiredCharacterLevel": 25
  },
  {
    "id": 140921,
    "characterMasterId": 140920,
    "episodeMasterId": 140921,
    "episodeOrder": "First",
    "requiredCharacterLevel": 1
  },
  {
    "id": 140922,
    "characterMasterId": 140920,
    "episodeMasterId": 140922,
    "episodeOrder": "Second",
    "requiredCharacterLevel": 25
  },
  {
    "id": 140931,
    "characterMasterId": 140930,
    "episodeMasterId": 140931,
    "episodeOrder": "First",
    "requiredCharacterLevel": 1
  },
  {
    "id": 140932,
    "characterMasterId": 140930,
    "episodeMasterId": 140932,
    "episodeOrder": "Second",
    "requiredCharacterLevel": 25
  },
  {
    "id": 140941,
    "characterMasterId": 140940,
    "episodeMasterId": 140941,
    "episodeOrder": "First",
    "requiredCharacterLevel": 1
  },
  {
    "id": 140942,
    "characterMasterId": 140940,
    "episodeMasterId": 140942,
    "episodeOrder": "Second",
    "requiredCharacterLevel": 25
  },
  {
    "id": 140951,
    "characterMasterId": 140950,
    "episodeMasterId": 140951,
    "episodeOrder": "First",
    "requiredCharacterLevel": 1
  },
  {
    "id": 140952,
    "characterMasterId": 140950,
    "episodeMasterId": 140952,
    "episodeOrder": "Second",
    "requiredCharacterLevel": 25
  },
  {
    "id": 140961,
    "characterMasterId": 140960,
    "episodeMasterId": 140961,
    "episodeOrder": "First",
    "requiredCharacterLevel": 1
  },
  {
    "id": 140962,
    "characterMasterId": 140960,
    "episodeMasterId": 140962,
    "episodeOrder": "Second",
    "requiredCharacterLevel": 25
  },
  {
    "id": 140971,
    "characterMasterId": 140970,
    "episodeMasterId": 140971,
    "episodeOrder": "First",
    "requiredCharacterLevel": 1
  },
  {
    "id": 140972,
    "characterMasterId": 140970,
    "episodeMasterId": 140972,
    "episodeOrder": "Second",
    "requiredCharacterLevel": 25
  },
  {
    "id": 140981,
    "characterMasterId": 140980,
    "episodeMasterId": 140981,
    "episodeOrder": "First",
    "requiredCharacterLevel": 1
  },
  {
    "id": 140982,
    "characterMasterId": 140980,
    "episodeMasterId": 140982,
    "episodeOrder": "Second",
    "requiredCharacterLevel": 25
  },
  {
    "id": 140991,
    "characterMasterId": 140990,
    "episodeMasterId": 140991,
    "episodeOrder": "First",
    "requiredCharacterLevel": 1
  },
  {
    "id": 140992,
    "characterMasterId": 140990,
    "episodeMasterId": 140992,
    "episodeOrder": "Second",
    "requiredCharacterLevel": 25
  },
  {
    "id": 141001,
    "characterMasterId": 141000,
    "episodeMasterId": 141001,
    "episodeOrder": "First",
    "requiredCharacterLevel": 1
  },
  {
    "id": 141002,
    "characterMasterId": 141000,
    "episodeMasterId": 141002,
    "episodeOrder": "Second",
    "requiredCharacterLevel": 25
  },
  {
    "id": 141011,
    "characterMasterId": 141010,
    "episodeMasterId": 141011,
    "episodeOrder": "First",
    "requiredCharacterLevel": 1
  },
  {
    "id": 141012,
    "characterMasterId": 141010,
    "episodeMasterId": 141012,
    "episodeOrder": "Second",
    "requiredCharacterLevel": 25
  },
  {
    "id": 141021,
    "characterMasterId": 141020,
    "episodeMasterId": 141021,
    "episodeOrder": "First",
    "requiredCharacterLevel": 1
  },
  {
    "id": 141022,
    "characterMasterId": 141020,
    "episodeMasterId": 141022,
    "episodeOrder": "Second",
    "requiredCharacterLevel": 25
  },
  {
    "id": 141031,
    "characterMasterId": 141030,
    "episodeMasterId": 141031,
    "episodeOrder": "First",
    "requiredCharacterLevel": 1
  },
  {
    "id": 141032,
    "characterMasterId": 141030,
    "episodeMasterId": 141032,
    "episodeOrder": "Second",
    "requiredCharacterLevel": 25
  },
  {
    "id": 141041,
    "characterMasterId": 141040,
    "episodeMasterId": 141041,
    "episodeOrder": "First",
    "requiredCharacterLevel": 1
  },
  {
    "id": 141042,
    "characterMasterId": 141040,
    "episodeMasterId": 141042,
    "episodeOrder": "Second",
    "requiredCharacterLevel": 25
  },
  {
    "id": 141051,
    "characterMasterId": 141050,
    "episodeMasterId": 141051,
    "episodeOrder": "First",
    "requiredCharacterLevel": 1
  },
  {
    "id": 141052,
    "characterMasterId": 141050,
    "episodeMasterId": 141052,
    "episodeOrder": "Second",
    "requiredCharacterLevel": 25
  },
  {
    "id": 141061,
    "characterMasterId": 141060,
    "episodeMasterId": 141061,
    "episodeOrder": "First",
    "requiredCharacterLevel": 1
  },
  {
    "id": 141062,
    "characterMasterId": 141060,
    "episodeMasterId": 141062,
    "episodeOrder": "Second",
    "requiredCharacterLevel": 25
  },
  {
    "id": 141071,
    "characterMasterId": 141070,
    "episodeMasterId": 141071,
    "episodeOrder": "First",
    "requiredCharacterLevel": 1
  },
  {
    "id": 141072,
    "characterMasterId": 141070,
    "episodeMasterId": 141072,
    "episodeOrder": "Second",
    "requiredCharacterLevel": 25
  },
  {
    "id": 141081,
    "characterMasterId": 141080,
    "episodeMasterId": 141081,
    "episodeOrder": "First",
    "requiredCharacterLevel": 1
  },
  {
    "id": 141082,
    "characterMasterId": 141080,
    "episodeMasterId": 141082,
    "episodeOrder": "Second",
    "requiredCharacterLevel": 25
  },
  {
    "id": 141091,
    "characterMasterId": 141090,
    "episodeMasterId": 141091,
    "episodeOrder": "First",
    "requiredCharacterLevel": 1
  },
  {
    "id": 141092,
    "characterMasterId": 141090,
    "episodeMasterId": 141092,
    "episodeOrder": "Second",
    "requiredCharacterLevel": 25
  },
  {
    "id": 141101,
    "characterMasterId": 141100,
    "episodeMasterId": 141101,
    "episodeOrder": "First",
    "requiredCharacterLevel": 1
  },
  {
    "id": 141102,
    "characterMasterId": 141100,
    "episodeMasterId": 141102,
    "episodeOrder": "Second",
    "requiredCharacterLevel": 25
  },
  {
    "id": 141111,
    "characterMasterId": 141110,
    "episodeMasterId": 141111,
    "episodeOrder": "First",
    "requiredCharacterLevel": 1
  },
  {
    "id": 141112,
    "characterMasterId": 141110,
    "episodeMasterId": 141112,
    "episodeOrder": "Second",
    "requiredCharacterLevel": 25
  },
  {
    "id": 141121,
    "characterMasterId": 141120,
    "episodeMasterId": 141121,
    "episodeOrder": "First",
    "requiredCharacterLevel": 1
  },
  {
    "id": 141122,
    "characterMasterId": 141120,
    "episodeMasterId": 141122,
    "episodeOrder": "Second",
    "requiredCharacterLevel": 25
  },
  {
    "id": 141131,
    "characterMasterId": 141130,
    "episodeMasterId": 141131,
    "episodeOrder": "First",
    "requiredCharacterLevel": 1
  },
  {
    "id": 141132,
    "characterMasterId": 141130,
    "episodeMasterId": 141132,
    "episodeOrder": "Second",
    "requiredCharacterLevel": 25
  },
  {
    "id": 141141,
    "characterMasterId": 141140,
    "episodeMasterId": 141141,
    "episodeOrder": "First",
    "requiredCharacterLevel": 1
  },
  {
    "id": 141142,
    "characterMasterId": 141140,
    "episodeMasterId": 141142,
    "episodeOrder": "Second",
    "requiredCharacterLevel": 25
  },
  {
    "id": 141151,
    "characterMasterId": 141150,
    "episodeMasterId": 141151,
    "episodeOrder": "First",
    "requiredCharacterLevel": 1
  },
  {
    "id": 141152,
    "characterMasterId": 141150,
    "episodeMasterId": 141152,
    "episodeOrder": "Second",
    "requiredCharacterLevel": 25
  },
  {
    "id": 141161,
    "characterMasterId": 141160,
    "episodeMasterId": 141161,
    "episodeOrder": "First",
    "requiredCharacterLevel": 1
  },
  {
    "id": 141162,
    "characterMasterId": 141160,
    "episodeMasterId": 141162,
    "episodeOrder": "Second",
    "requiredCharacterLevel": 25
  },
  {
    "id": 141171,
    "characterMasterId": 141170,
    "episodeMasterId": 141171,
    "episodeOrder": "First",
    "requiredCharacterLevel": 1
  },
  {
    "id": 141172,
    "characterMasterId": 141170,
    "episodeMasterId": 141172,
    "episodeOrder": "Second",
    "requiredCharacterLevel": 25
  },
  {
    "id": 141181,
    "characterMasterId": 141180,
    "episodeMasterId": 141181,
    "episodeOrder": "First",
    "requiredCharacterLevel": 1
  },
  {
    "id": 141182,
    "characterMasterId": 141180,
    "episodeMasterId": 141182,
    "episodeOrder": "Second",
    "requiredCharacterLevel": 25
  },
  {
    "id": 141191,
    "characterMasterId": 141190,
    "episodeMasterId": 141191,
    "episodeOrder": "First",
    "requiredCharacterLevel": 1
  },
  {
    "id": 141192,
    "characterMasterId": 141190,
    "episodeMasterId": 141192,
    "episodeOrder": "Second",
    "requiredCharacterLevel": 25
  },
  {
    "id": 141201,
    "characterMasterId": 141200,
    "episodeMasterId": 141201,
    "episodeOrder": "First",
    "requiredCharacterLevel": 1
  },
  {
    "id": 141202,
    "characterMasterId": 141200,
    "episodeMasterId": 141202,
    "episodeOrder": "Second",
    "requiredCharacterLevel": 25
  },
  {
    "id": 141211,
    "characterMasterId": 141210,
    "episodeMasterId": 141211,
    "episodeOrder": "First",
    "requiredCharacterLevel": 1
  },
  {
    "id": 141212,
    "characterMasterId": 141210,
    "episodeMasterId": 141212,
    "episodeOrder": "Second",
    "requiredCharacterLevel": 25
  },
  {
    "id": 141221,
    "characterMasterId": 141220,
    "episodeMasterId": 141221,
    "episodeOrder": "First",
    "requiredCharacterLevel": 1
  },
  {
    "id": 141222,
    "characterMasterId": 141220,
    "episodeMasterId": 141222,
    "episodeOrder": "Second",
    "requiredCharacterLevel": 25
  },
  {
    "id": 141231,
    "characterMasterId": 141230,
    "episodeMasterId": 141231,
    "episodeOrder": "First",
    "requiredCharacterLevel": 1
  },
  {
    "id": 141232,
    "characterMasterId": 141230,
    "episodeMasterId": 141232,
    "episodeOrder": "Second",
    "requiredCharacterLevel": 25
  },
  {
    "id": 141241,
    "characterMasterId": 141240,
    "episodeMasterId": 141241,
    "episodeOrder": "First",
    "requiredCharacterLevel": 1
  },
  {
    "id": 141242,
    "characterMasterId": 141240,
    "episodeMasterId": 141242,
    "episodeOrder": "Second",
    "requiredCharacterLevel": 25
  },
  {
    "id": 141251,
    "characterMasterId": 141250,
    "episodeMasterId": 141251,
    "episodeOrder": "First",
    "requiredCharacterLevel": 1
  },
  {
    "id": 141252,
    "characterMasterId": 141250,
    "episodeMasterId": 141252,
    "episodeOrder": "Second",
    "requiredCharacterLevel": 25
  },
  {
    "id": 141261,
    "characterMasterId": 141260,
    "episodeMasterId": 141261,
    "episodeOrder": "First",
    "requiredCharacterLevel": 1
  },
  {
    "id": 141262,
    "characterMasterId": 141260,
    "episodeMasterId": 141262,
    "episodeOrder": "Second",
    "requiredCharacterLevel": 25
  },
  {
    "id": 141271,
    "characterMasterId": 141270,
    "episodeMasterId": 141271,
    "episodeOrder": "First",
    "requiredCharacterLevel": 1
  },
  {
    "id": 141272,
    "characterMasterId": 141270,
    "episodeMasterId": 141272,
    "episodeOrder": "Second",
    "requiredCharacterLevel": 25
  },
  {
    "id": 141281,
    "characterMasterId": 141280,
    "episodeMasterId": 141281,
    "episodeOrder": "First",
    "requiredCharacterLevel": 1
  },
  {
    "id": 141282,
    "characterMasterId": 141280,
    "episodeMasterId": 141282,
    "episodeOrder": "Second",
    "requiredCharacterLevel": 25
  },
  {
    "id": 141291,
    "characterMasterId": 141290,
    "episodeMasterId": 141291,
    "episodeOrder": "First",
    "requiredCharacterLevel": 1
  },
  {
    "id": 141292,
    "characterMasterId": 141290,
    "episodeMasterId": 141292,
    "episodeOrder": "Second",
    "requiredCharacterLevel": 25
  },
  {
    "id": 141301,
    "characterMasterId": 141300,
    "episodeMasterId": 141301,
    "episodeOrder": "First",
    "requiredCharacterLevel": 1
  },
  {
    "id": 141302,
    "characterMasterId": 141300,
    "episodeMasterId": 141302,
    "episodeOrder": "Second",
    "requiredCharacterLevel": 25
  },
  {
    "id": 141311,
    "characterMasterId": 141310,
    "episodeMasterId": 141311,
    "episodeOrder": "First",
    "requiredCharacterLevel": 1
  },
  {
    "id": 141312,
    "characterMasterId": 141310,
    "episodeMasterId": 141312,
    "episodeOrder": "Second",
    "requiredCharacterLevel": 25
  },
  {
    "id": 141321,
    "characterMasterId": 141320,
    "episodeMasterId": 141321,
    "episodeOrder": "First",
    "requiredCharacterLevel": 1
  },
  {
    "id": 141322,
    "characterMasterId": 141320,
    "episodeMasterId": 141322,
    "episodeOrder": "Second",
    "requiredCharacterLevel": 25
  },
  {
    "id": 141331,
    "characterMasterId": 141330,
    "episodeMasterId": 141331,
    "episodeOrder": "First",
    "requiredCharacterLevel": 1
  },
  {
    "id": 141332,
    "characterMasterId": 141330,
    "episodeMasterId": 141332,
    "episodeOrder": "Second",
    "requiredCharacterLevel": 25
  },
  {
    "id": 141341,
    "characterMasterId": 141340,
    "episodeMasterId": 141341,
    "episodeOrder": "First",
    "requiredCharacterLevel": 1
  },
  {
    "id": 141342,
    "characterMasterId": 141340,
    "episodeMasterId": 141342,
    "episodeOrder": "Second",
    "requiredCharacterLevel": 25
  },
  {
    "id": 141351,
    "characterMasterId": 141350,
    "episodeMasterId": 141351,
    "episodeOrder": "First",
    "requiredCharacterLevel": 1
  },
  {
    "id": 141352,
    "characterMasterId": 141350,
    "episodeMasterId": 141352,
    "episodeOrder": "Second",
    "requiredCharacterLevel": 25
  },
  {
    "id": 141361,
    "characterMasterId": 141360,
    "episodeMasterId": 141361,
    "episodeOrder": "First",
    "requiredCharacterLevel": 1
  },
  {
    "id": 141362,
    "characterMasterId": 141360,
    "episodeMasterId": 141362,
    "episodeOrder": "Second",
    "requiredCharacterLevel": 25
  },
  {
    "id": 141371,
    "characterMasterId": 141370,
    "episodeMasterId": 141371,
    "episodeOrder": "First",
    "requiredCharacterLevel": 1
  },
  {
    "id": 141372,
    "characterMasterId": 141370,
    "episodeMasterId": 141372,
    "episodeOrder": "Second",
    "requiredCharacterLevel": 25
  },
  {
    "id": 141381,
    "characterMasterId": 141380,
    "episodeMasterId": 141381,
    "episodeOrder": "First",
    "requiredCharacterLevel": 1
  },
  {
    "id": 141382,
    "characterMasterId": 141380,
    "episodeMasterId": 141382,
    "episodeOrder": "Second",
    "requiredCharacterLevel": 25
  },
  {
    "id": 141391,
    "characterMasterId": 141390,
    "episodeMasterId": 141391,
    "episodeOrder": "First",
    "requiredCharacterLevel": 1
  },
  {
    "id": 141392,
    "characterMasterId": 141390,
    "episodeMasterId": 141392,
    "episodeOrder": "Second",
    "requiredCharacterLevel": 25
  },
  {
    "id": 141401,
    "characterMasterId": 141400,
    "episodeMasterId": 141401,
    "episodeOrder": "First",
    "requiredCharacterLevel": 1
  },
  {
    "id": 141402,
    "characterMasterId": 141400,
    "episodeMasterId": 141402,
    "episodeOrder": "Second",
    "requiredCharacterLevel": 25
  },
  {
    "id": 141411,
    "characterMasterId": 141410,
    "episodeMasterId": 141411,
    "episodeOrder": "First",
    "requiredCharacterLevel": 1
  },
  {
    "id": 141412,
    "characterMasterId": 141410,
    "episodeMasterId": 141412,
    "episodeOrder": "Second",
    "requiredCharacterLevel": 25
  },
  {
    "id": 141421,
    "characterMasterId": 141420,
    "episodeMasterId": 141421,
    "episodeOrder": "First",
    "requiredCharacterLevel": 1
  },
  {
    "id": 141422,
    "characterMasterId": 141420,
    "episodeMasterId": 141422,
    "episodeOrder": "Second",
    "requiredCharacterLevel": 25
  },
  {
    "id": 141431,
    "characterMasterId": 141430,
    "episodeMasterId": 141431,
    "episodeOrder": "First",
    "requiredCharacterLevel": 1
  },
  {
    "id": 141432,
    "characterMasterId": 141430,
    "episodeMasterId": 141432,
    "episodeOrder": "Second",
    "requiredCharacterLevel": 25
  },
  {
    "id": 141441,
    "characterMasterId": 141440,
    "episodeMasterId": 141441,
    "episodeOrder": "First",
    "requiredCharacterLevel": 1
  },
  {
    "id": 141442,
    "characterMasterId": 141440,
    "episodeMasterId": 141442,
    "episodeOrder": "Second",
    "requiredCharacterLevel": 25
  },
  {
    "id": 141451,
    "characterMasterId": 141450,
    "episodeMasterId": 141451,
    "episodeOrder": "First",
    "requiredCharacterLevel": 1
  },
  {
    "id": 141452,
    "characterMasterId": 141450,
    "episodeMasterId": 141452,
    "episodeOrder": "Second",
    "requiredCharacterLevel": 25
  },
  {
    "id": 141461,
    "characterMasterId": 141460,
    "episodeMasterId": 141461,
    "episodeOrder": "First",
    "requiredCharacterLevel": 1
  },
  {
    "id": 141462,
    "characterMasterId": 141460,
    "episodeMasterId": 141462,
    "episodeOrder": "Second",
    "requiredCharacterLevel": 25
  },
  {
    "id": 141471,
    "characterMasterId": 141470,
    "episodeMasterId": 141471,
    "episodeOrder": "First",
    "requiredCharacterLevel": 1
  },
  {
    "id": 141472,
    "characterMasterId": 141470,
    "episodeMasterId": 141472,
    "episodeOrder": "Second",
    "requiredCharacterLevel": 25
  },
  {
    "id": 141481,
    "characterMasterId": 141480,
    "episodeMasterId": 141481,
    "episodeOrder": "First",
    "requiredCharacterLevel": 1
  },
  {
    "id": 141482,
    "characterMasterId": 141480,
    "episodeMasterId": 141482,
    "episodeOrder": "Second",
    "requiredCharacterLevel": 25
  },
  {
    "id": 141491,
    "characterMasterId": 141490,
    "episodeMasterId": 141491,
    "episodeOrder": "First",
    "requiredCharacterLevel": 1
  },
  {
    "id": 141492,
    "characterMasterId": 141490,
    "episodeMasterId": 141492,
    "episodeOrder": "Second",
    "requiredCharacterLevel": 25
  },
  {
    "id": 141501,
    "characterMasterId": 141500,
    "episodeMasterId": 141501,
    "episodeOrder": "First",
    "requiredCharacterLevel": 1
  },
  {
    "id": 141502,
    "characterMasterId": 141500,
    "episodeMasterId": 141502,
    "episodeOrder": "Second",
    "requiredCharacterLevel": 25
  },
  {
    "id": 141511,
    "characterMasterId": 141510,
    "episodeMasterId": 141511,
    "episodeOrder": "First",
    "requiredCharacterLevel": 1
  },
  {
    "id": 141512,
    "characterMasterId": 141510,
    "episodeMasterId": 141512,
    "episodeOrder": "Second",
    "requiredCharacterLevel": 25
  },
  {
    "id": 141521,
    "characterMasterId": 141520,
    "episodeMasterId": 141521,
    "episodeOrder": "First",
    "requiredCharacterLevel": 1
  },
  {
    "id": 141522,
    "characterMasterId": 141520,
    "episodeMasterId": 141522,
    "episodeOrder": "Second",
    "requiredCharacterLevel": 25
  },
  {
    "id": 141531,
    "characterMasterId": 141530,
    "episodeMasterId": 141531,
    "episodeOrder": "First",
    "requiredCharacterLevel": 1
  },
  {
    "id": 141532,
    "characterMasterId": 141530,
    "episodeMasterId": 141532,
    "episodeOrder": "Second",
    "requiredCharacterLevel": 25
  },
  {
    "id": 141541,
    "characterMasterId": 141540,
    "episodeMasterId": 141541,
    "episodeOrder": "First",
    "requiredCharacterLevel": 1
  },
  {
    "id": 141542,
    "characterMasterId": 141540,
    "episodeMasterId": 141542,
    "episodeOrder": "Second",
    "requiredCharacterLevel": 25
  },
  {
    "id": 141551,
    "characterMasterId": 141550,
    "episodeMasterId": 141551,
    "episodeOrder": "First",
    "requiredCharacterLevel": 1
  },
  {
    "id": 141552,
    "characterMasterId": 141550,
    "episodeMasterId": 141552,
    "episodeOrder": "Second",
    "requiredCharacterLevel": 25
  },
  {
    "id": 141561,
    "characterMasterId": 141560,
    "episodeMasterId": 141561,
    "episodeOrder": "First",
    "requiredCharacterLevel": 1
  },
  {
    "id": 141562,
    "characterMasterId": 141560,
    "episodeMasterId": 141562,
    "episodeOrder": "Second",
    "requiredCharacterLevel": 25
  }
]